{
    "containers": {
        "CONT4": {
            "items": {
                "HAH": [
                    {
                        "count": 1,
                        "_id": "60bc46cab08109216ca96aff",
                        "name": "huh",
                        "timeAdded": "09/13/2021"
                    },
                    {
                        "count": 3,
                        "_id": "60bd73c2f421020dd007aab9",
                        "name": "hah",
                        "timeAdded": "6/5/2021"
                    }
                ]
            },
            "layout": {
                "tiles": [],
                "size": [
                    4,
                    4
                ]
            },
            "_id": "60b41b135356d108c8ff786d",
            "name": "cont4",
            "createdAt": "2021-05-30T23:09:12.963Z",
            "updatedAt": "2021-06-09T19:22:48.831Z"
        }
    },
    "itemHistory": {
        "HAH": {
            "lifetime": 15,
            "_id": "60b5437046fa2421b4ea8800",
            "name": "hah",
            "createdAt": "2021-05-31T20:13:36.435Z",
            "updatedAt": "2021-06-09T19:22:48.832Z"
        },
        "HUH": {
            "lifetime": 15,
            "_id": "60b5437046fa2421b4ea8800",
            "name": "hah",
            "createdAt": "2021-05-31T20:13:36.435Z",
            "updatedAt": "2021-06-09T19:22:48.832Z"
        }
    },
    "_id": "60b303e782c249181cfbc19b",
    "name": "mad",
    "createdAt": "2021-05-30T03:17:59.942Z",
    "updatedAt": "2021-06-09T19:22:48.832Z",
    "__v": 1
}